binarybeech/__init__.py
binarybeech/attributehandler.py
binarybeech/binarybeech.py
binarybeech/datamanager.py
binarybeech/extra.py
binarybeech/math.py
binarybeech/metrics.py
binarybeech/minimizer.py
binarybeech/missingshandler.py
binarybeech/reporter.py
binarybeech/trainingdata.py
binarybeech/tree.py
binarybeech/utils.py
binarybeech/visualize.py
binarybeech-0.3.1.dist-info/METADATA
binarybeech-0.3.1.dist-info/WHEEL
binarybeech-0.3.1.dist-info/licenses/LICENSE
binarybeech-0.3.1.dist-info/RECORD
