Metadata-Version: 2.1
Name: binarybeech
Version: 0.3.1
Summary: Simplistic algorithms to train decision trees for regression and classification
Project-URL: Homepage, https://github.com/arminwitte/binarybeech
Project-URL: Bug Tracker, https://github.com/arminwitte/binarybeech/issues
Author: Armin Witte
License: MIT License
License-File: LICENSE
Keywords: decision tree,machine learning,supervised learning,unsupervised learning
Classifier: License :: OSI Approved :: MIT License
Classifier: Operating System :: OS Independent
Classifier: Programming Language :: Python :: 3
Requires-Python: >=3.7
Requires-Dist: numpy>=1.19.0
Requires-Dist: pandas>=1.3.0
Requires-Dist: scipy>=1.7.0
Provides-Extra: visualize
Requires-Dist: matplotlib; extra == 'visualize'
Requires-Dist: treelib; extra == 'visualize'
